README.md
setup.py
rahulworld_distributions/Binomialdistribution.py
rahulworld_distributions/Gaussiandistribution.py
rahulworld_distributions/Generaldistribution.py
rahulworld_distributions/__init__.py
rahulworld_distributions.egg-info/PKG-INFO
rahulworld_distributions.egg-info/SOURCES.txt
rahulworld_distributions.egg-info/dependency_links.txt
rahulworld_distributions.egg-info/not-zip-safe
rahulworld_distributions.egg-info/top_level.txt